ensurepath.py
ensurepath-0.2.6.dist-info/LICENSE.md
ensurepath-0.2.6.dist-info/METADATA
ensurepath-0.2.6.dist-info/WHEEL
ensurepath-0.2.6.dist-info/top_level.txt
ensurepath-0.2.6.dist-info/RECORD
