Metadata-Version: 2.1
Name: ensurepath
Version: 0.2.6
Summary: Ensure python, pip and with pip installed binarys (scripts for win) are in your PATH variable.
Author: Konxell
Maintainer: Konxell
License: Unlicense (Public Domain)
Project-URL: Issues, https://github.com/knoxell/ensurepath/issues
Project-URL: Repository, https://github.com/knoxell/ensurepath
Keywords: path,user path,windows,linux,msstore,ms store,terminal
Classifier: Development Status :: 4 - Beta
Classifier: Intended Audience :: End Users/Desktop
Classifier: License :: OSI Approved :: The Unlicense (Unlicense)
Classifier: License :: Public Domain
Classifier: Programming Language :: Python :: 3.7
Classifier: Programming Language :: Python :: 3.8
Classifier: Programming Language :: Python :: 3.9
Classifier: Programming Language :: Python :: 3.10
Classifier: Programming Language :: Python :: 3.11
Classifier: Programming Language :: Python :: Implementation :: CPython
Classifier: Programming Language :: Python :: Implementation :: PyPy
Requires-Python: >=3.7
License-File: LICENSE.md
Requires-Dist: pip
Requires-Dist: userpath~=1.9.2
